watermarker/__init__.py
watermarker/admin.py
watermarker/conf.py
watermarker/models.py
watermarker/utils.py
watermarker/locale/ru/LC_MESSAGES/django.mo
watermarker/locale/ru/LC_MESSAGES/django.po
watermarker/migrations/0001_initial.py
watermarker/migrations/__init__.py
watermarker/south_migrations/0001_initial.py
watermarker/south_migrations/__init__.py
watermarker/templatetags/__init__.py
watermarker/templatetags/watermark.py
watermarker/tests/__init__.py
watermarker/tests/test_utils.py
django3_watermark-0.2.0.dist-info/LICENSE
django3_watermark-0.2.0.dist-info/METADATA
django3_watermark-0.2.0.dist-info/WHEEL
django3_watermark-0.2.0.dist-info/top_level.txt
django3_watermark-0.2.0.dist-info/RECORD
