Metadata-Version: 2.1
Name: django3-watermark
Version: 0.2.0
Summary: Quick and efficient way to apply watermarks to images in Django.
Home-page: http://github.com/ojengwa/django-watermark/
Author: Josh VanderLinden
Author-email: codekoala@gmail.com
Maintainer: Bernard Ojengwa
Maintainer-email: bernardojengwa@gmail.com
License: BSD License
Keywords: django,watermark,image,photo,logo
Platform: UNKNOWN
Classifier: Development Status :: 5 - Production/Stable
Classifier: Environment :: Web Environment
Classifier: Framework :: Django
Classifier: Intended Audience :: Developers
Classifier: Intended Audience :: End Users/Desktop
Classifier: License :: OSI Approved :: BSD License
Classifier: Natural Language :: English
Classifier: Operating System :: OS Independent
Classifier: Programming Language :: Python :: 2
Classifier: Programming Language :: Python :: 2.7
Classifier: Programming Language :: Python :: 3
Classifier: Programming Language :: Python :: 3.4
Classifier: Topic :: Artistic Software
Classifier: Topic :: Internet :: WWW/HTTP
Classifier: Topic :: Internet :: WWW/HTTP :: Dynamic Content
Classifier: Topic :: Multimedia :: Graphics
Requires-Dist: django (>=1.4)
Requires-Dist: django-appconf
Requires-Dist: pillow
Requires-Dist: six
